{
  "gitSyncId": "673641b0d277b70972705e64_3fe99d58-afdb-4803-a305-41f0809873ee",
  "unpublishedPage": {
    "isHidden": false,
    "layouts": [
      {
        "dsl": {
          "backgroundColor": "none",
          "bottomRow": 380,
          "canExtend": true,
          "containerStyle": "none",
          "detachFromLayout": true,
          "dynamicBindingPathList": [],
          "leftColumn": 0,
          "minHeight": 780,
          "parentColumnSpace": 1,
          "parentRowSpace": 1,
          "rightColumn": 1224,
          "snapColumns": 64,
          "snapRows": 76,
          "topRow": 0,
          "type": "CANVAS_WIDGET",
          "version": 90,
          "widgetId": "0",
          "widgetName": "MainContainer"
        }
      }
    ],
    "name": "AssistenteDashboard",
    "slug": "assistentedashboard"
  }
}